<?xml version="1.0" encoding="utf-8"?>
<!DOCTYPE hibernate-mapping PUBLIC "-//Hibernate/Hibernate Mapping DTD 3.0//EN"
"http://hibernate.sourceforge.net/hibernate-mapping-3.0.dtd">
<!-- 
    Mapping file autogenerated by MyEclipse Persistence Tools
-->
<hibernate-mapping>
    <class name="com.wondersgroup.base.login.model.TbAuthResource" table="TB_AUTH_RESOURCE">
        <id name="resid" type="java.lang.String">
            <column name="resid" length="36"  />
            <generator class="increment" />
        </id>
        <many-to-one name="tbAuthResource" class="com.wondersgroup.base.login.model.TbAuthResource" fetch="select" lazy="false">
            <column name="presid" precision="22" scale="0" />
        </many-to-one>
        <property name="resname" type="java.lang.String">
            <column name="resname" length="100" not-null="true" />
        </property>
        <property name="keyword" type="java.lang.String">
            <column name="keyword" length="50" not-null="true" />
        </property>
        <property name="url" type="java.lang.String">
            <column name="url" length="200" />
        </property>
        <property name="comments" type="java.lang.String">
            <column name="comments" length="100" />
        </property>
        <property name="resLevel" type="java.lang.Long">
            <column name="res_level" precision="22" scale="0" not-null="true" />
        </property>
        <property name="treelayer" type="java.lang.String">
            <column name="tree_layer" length="12" not-null="true" />
        </property>
        <set name="tbAuthRoles" inverse="true" table="TB_AUTH_ROLE_RESOURCE">
            <key>
                <column name="resid" precision="22" scale="0" />
            </key>
            <many-to-many entity-name="com.wondersgroup.base.login.model.TbAuthRole">
                <column name="roleid" precision="22" scale="0" />
            </many-to-many>
        </set>
        <set name="tbAuthResources" inverse="true">
            <key>
                <column name="presid" precision="22" scale="0" />
            </key>
            <one-to-many class="com.wondersgroup.base.login.model.TbAuthResource"/>
        </set>
    </class>
</hibernate-mapping>
